unlearun/__init__.py
unlearun/core.py
unlearun/methods/__init__.py
unlearun/methods/base.py
unlearun/methods/dpo.py
unlearun/methods/grad_ascent.py
unlearun/methods/grad_diff.py
unlearun-0.0.1.dist-info/licenses/LICENSE
unlearun-0.0.1.dist-info/METADATA
unlearun-0.0.1.dist-info/WHEEL
unlearun-0.0.1.dist-info/top_level.txt
unlearun-0.0.1.dist-info/RECORD
